apple_newton/__init__.py
apple_newton/_version.py
apple_newton/check_python.py
apple_newton/hello.py
apple_newton/main.py
apple_newton-0.0.3.dist-info/METADATA
apple_newton-0.0.3.dist-info/WHEEL
apple_newton-0.0.3.dist-info/licenses/LICENSE
apple_newton-0.0.3.dist-info/RECORD
