Metadata-Version: 2.4
Name: apple_newton
Version: 0.0.3
Summary: A Simple Modern Python Project With UV
Author-email: Hiroshi Fujiwara <hiroshi.829f@gmail.com>
License: MIT License
License-File: LICENSE
Classifier: Programming Language :: Python
Classifier: Programming Language :: Python :: 3
Classifier: Programming Language :: Python :: 3.13
Classifier: Topic :: Software Development :: Libraries :: Python Modules
Requires-Python: >=3.13
